road_collisions_base/__init__.py
road_collisions_base/constants.py
road_collisions_base/logging.py
road_collisions_base/utils.py
road_collisions_base/bin/__init__.py
road_collisions_base/bin/load.py
road_collisions_base/models/__init__.py
road_collisions_base/models/collision.py
road_collisions_base/models/generic.py
road_collisions_base/models/raw_collision.py
road_collisions_base-0.0.22.dist-info/LICENSE
road_collisions_base-0.0.22.dist-info/METADATA
road_collisions_base-0.0.22.dist-info/WHEEL
road_collisions_base-0.0.22.dist-info/entry_points.txt
road_collisions_base-0.0.22.dist-info/top_level.txt
road_collisions_base-0.0.22.dist-info/RECORD
