Metadata-Version: 2.1
Name: road-collisions-base
Version: 0.0.22
Summary: Road collision base
Home-page: https://github.com/RobertLucey/road-collisions-base
Author: Robert Lucey
License: UNKNOWN
Platform: UNKNOWN
Requires-Python: >=3.6
License-File: LICENSE
Requires-Dist: pandas
